Metadata-Version: 2.4
Name: axon-dl
Version: 0.1.3
Summary: A Deep Learning Library with focus on fast experimentation.
Author: Yusuf Shihata (Vixel)
Project-URL: Homepage, https://github.com/Vixel2006/axon
Project-URL: Bug Tracker, https://github.com/Vixel2006/axon/issues
Classifier: Programming Language :: Python :: 3
Classifier: License :: OSI Approved :: MIT License
Classifier: Operating System :: OS Independent
Classifier: Topic :: Scientific/Engineering :: Artificial Intelligence
Classifier: Development Status :: 3 - Alpha
Requires-Python: >=3.9
Requires-Dist: numpy
Requires-Dist: pyyaml
